viziocontroller/__init__.py
viziocontroller/api.py
viziocontroller/constants.py
viziocontroller/discover.py
viziocontroller/settings.py
viziocontroller-0.1.5.dist-info/METADATA
viziocontroller-0.1.5.dist-info/WHEEL
viziocontroller-0.1.5.dist-info/top_level.txt
viziocontroller-0.1.5.dist-info/RECORD
