Metadata-Version: 2.1
Name: viziocontroller
Version: 0.1.5
Summary: Vizio Controller
Home-page: https://github.com/48723247842/VizioController
Author: 7435171
Author-email: 48723247842@protonmail.com
Classifier: Programming Language :: Python :: 3
Classifier: License :: OSI Approved :: MIT License
Classifier: Operating System :: OS Independent
Requires-Python: >=3.8
Requires-Dist: netifaces (>=0.10.9)
Requires-Dist: requests (>=2.24.0)
Requires-Dist: tqdm (>=4.48.2)
Requires-Dist: wakeonlan (>=2.1.0)
